pycryptodome_test_vectors/__init__.py
pycryptodome_test_vectors/Cipher/AES/CBCGFSbox128.rsp
pycryptodome_test_vectors/Cipher/AES/CBCGFSbox192.rsp
pycryptodome_test_vectors/Cipher/AES/CBCGFSbox256.rsp
pycryptodome_test_vectors/Cipher/AES/CBCKeySbox128.rsp
pycryptodome_test_vectors/Cipher/AES/CBCKeySbox192.rsp
pycryptodome_test_vectors/Cipher/AES/CBCKeySbox256.rsp
pycryptodome_test_vectors/Cipher/AES/CBCMCT128.rsp
pycryptodome_test_vectors/Cipher/AES/CBCMCT192.rsp
pycryptodome_test_vectors/Cipher/AES/CBCMCT256.rsp
pycryptodome_test_vectors/Cipher/AES/CBCMMT128.rsp
pycryptodome_test_vectors/Cipher/AES/CBCMMT192.rsp
pycryptodome_test_vectors/Cipher/AES/CBCMMT256.rsp
pycryptodome_test_vectors/Cipher/AES/CBCVarKey128.rsp
pycryptodome_test_vectors/Cipher/AES/CBCVarKey192.rsp
pycryptodome_test_vectors/Cipher/AES/CBCVarKey256.rsp
pycryptodome_test_vectors/Cipher/AES/CBCVarTxt128.rsp
pycryptodome_test_vectors/Cipher/AES/CBCVarTxt192.rsp
pycryptodome_test_vectors/Cipher/AES/CBCVarTxt256.rsp
pycryptodome_test_vectors/Cipher/AES/CFB128GFSbox128.rsp
pycryptodome_test_vectors/Cipher/AES/CFB128GFSbox192.rsp
pycryptodome_test_vectors/Cipher/AES/CFB128GFSbox256.rsp
pycryptodome_test_vectors/Cipher/AES/CFB128KeySbox128.rsp
pycryptodome_test_vectors/Cipher/AES/CFB128KeySbox192.rsp
pycryptodome_test_vectors/Cipher/AES/CFB128KeySbox256.rsp
pycryptodome_test_vectors/Cipher/AES/CFB128MCT128.rsp
pycryptodome_test_vectors/Cipher/AES/CFB128MCT192.rsp
pycryptodome_test_vectors/Cipher/AES/CFB128MCT256.rsp
pycryptodome_test_vectors/Cipher/AES/CFB128MMT128.rsp
pycryptodome_test_vectors/Cipher/AES/CFB128MMT192.rsp
pycryptodome_test_vectors/Cipher/AES/CFB128MMT256.rsp
pycryptodome_test_vectors/Cipher/AES/CFB128VarKey128.rsp
pycryptodome_test_vectors/Cipher/AES/CFB128VarKey192.rsp
pycryptodome_test_vectors/Cipher/AES/CFB128VarKey256.rsp
pycryptodome_test_vectors/Cipher/AES/CFB128VarTxt128.rsp
pycryptodome_test_vectors/Cipher/AES/CFB128VarTxt192.rsp
pycryptodome_test_vectors-1.0.12.dist-info/LICENSE.rst
pycryptodome_test_vectors-1.0.12.dist-info/METADATA
pycryptodome_test_vectors-1.0.12.dist-info/WHEEL
pycryptodome_test_vectors-1.0.12.dist-info/top_level.txt
pycryptodome_test_vectors-1.0.12.dist-info/RECORD
