Metadata-Version: 1.0
Name: pycryptodome-test-vectors
Version: 1.0.12
Summary: Test vectors for PyCryptodome
Home-page: https://www.pycryptodome.org
Author: Helder Eijs
Author-email: helderijs@gmail.com
License: BSD, Apache
Platform: Posix; MacOS X; Windows
